pylint_fail_under/__init__.py
pylint_fail_under/__main__.py
pylint_fail_under/tests/__init__.py
pylint_fail_under/tests/test_cmd_line_interface.py
pylint_fail_under-0.3.0.dist-info/LICENSE
pylint_fail_under-0.3.0.dist-info/METADATA
pylint_fail_under-0.3.0.dist-info/WHEEL
pylint_fail_under-0.3.0.dist-info/entry_points.txt
pylint_fail_under-0.3.0.dist-info/top_level.txt
pylint_fail_under-0.3.0.dist-info/RECORD
