Metadata-Version: 1.2
Name: pylint-fail-under
Version: 0.3.0
Summary: Pylint wrapper that verifies code reaches a minimum quality score.
Home-page: https://github.com/TNThieding/pylint-fail-under
Author: Tyler N. Thieding
Author-email: python@thieding.com
Maintainer: Tyler N. Thieding
Maintainer-email: python@thieding.com
License: MIT License
Download-URL: https://github.com/TNThieding/pylint-fail-under
Platform: UNKNOWN
Classifier: Development Status :: 4 - Beta
Classifier: Environment :: Console
Classifier: Intended Audience :: Developers
Classifier: License :: OSI Approved :: MIT License
Classifier: Natural Language :: English
Classifier: Operating System :: OS Independent
Classifier: Programming Language :: Python
Classifier: Topic :: Software Development :: Quality Assurance
